{
  "variables": [
    {
      "code": "STEP",
      "initial": 0,
      "max": "",
      "min": 0
    },
    {
      "code": "GOLD",
      "initial": 100,
      "max": "",
      "min": 0
    },
    {
      "code": "NEW_VAR",
      "initial": 0,
      "max": "",
      "min": ""
    }
  ],
  "events": [
    {
      "imageUrl": "",
      "title": {
        "en": "New Event",
        "ru": "Новое событие"
      },
      "text": {
        "en": "New Event English Description Text",
        "ru": "Новой событие описанное на русском языке"
      },
      "type": 1,
      "voiceUrl": {
        "ru": "",
        "en": ""
      },
      "conditionBlock": {
        "conditionType": 1,
        "conditions": [
          {
            "variableCode": "STEP",
            "sign": 2,
            "value": 5
          },
          {
            "variableCode": "GOLD",
            "sign": 1,
            "value": 1
          },
          {
            "conditionType": 2,
            "conditions": [
              {
                "variableCode": "GOLD",
                "sign": 1,
                "value": 1
              },
              {
                "variableCode": "STEP",
                "sign": 1,
                "value": 5
              }
            ]
          }
        ]
      },
      "answers": []
    },
    {
      "imageUrl": "",
      "title": {
        "en": "New Event",
        "ru": "Новое событие"
      },
      "text": {
        "en": "New Event English Description Text",
        "ru": "Новой событие описанное на русском языке"
      },
      "type": 1,
      "voiceUrl": {
        "ru": "",
        "en": ""
      },
      "conditionBlock": {
        "conditionType": 1,
        "conditions": [
          {
            "variableCode": "STEP",
            "sign": 1,
            "value": 1
          },
          {
            "variableCode": "GOLD",
            "sign": 2,
            "value": 1
          },
          {
            "conditionType": 2,
            "conditions": [
              {
                "variableCode": "STEP",
                "sign": 1,
                "value": 1
              },
              {
                "variableCode": "STEP",
                "sign": 1,
                "value": 5
              }
            ],
            "type": 2
          }
        ],
        "type": 1
      },
      "answers": [
        {
          "conditionBlock": {
            "conditions": [],
            "type": 1
          },
          "text": {
            "en": "Do something good",
            "ru": "Сделать что-нибудь хорошее"
          },
          "imageUrl": "",
          "voiceUrl": {
            "en": "",
            "ru": ""
          },
          "rewards": [
            {
              "variableCode": "GOLD",
              "operation": 1,
              "value": 10
            },
            {
              "variableCode": "GOLD",
              "value": -9
            },
            {
              "variableCode": "GOLD",
              "value": 1
            }
          ]
        },
        {
          "conditionBlock": {
            "conditions": [],
            "type": 1
          },
          "text": {
            "en": "Do something bad",
            "ru": "Сделать что-нибудь плохое"
          },
          "imageUrl": "",
          "voiceUrl": {
            "en": "",
            "ru": ""
          },
          "rewards": [
            {
              "variableCode": "GOLD",
              "value": -3
            },
            {
              "variableCode": "GOLD",
              "value": 1
            }
          ]
        },
        {
          "conditionBlock": {
            "conditions": [],
            "type": 1
          },
          "text": {
            "en": "Do something good",
            "ru": "Сделать что-нибудь хорошее"
          },
          "imageUrl": "",
          "voiceUrl": {
            "en": "",
            "ru": ""
          },
          "rewards": []
        }
      ]
    },
    {
      "imageUrl": "",
      "title": {
        "en": "Gold ended",
        "ru": "Закончилось золото"
      },
      "text": {
        "en": "(ENG)У вас в казне совершенно не осталось ни одной монетки",
        "ru": "У вас в казне совершенно не осталось ни одной монетки"
      },
      "type": 3,
      "voiceUrl": {
        "ru": "",
        "en": ""
      },
      "conditionBlock": {
        "type": 1,
        "conditions": [
          {
            "variableCode": "GOLD",
            "sign": 2,
            "value": 0
          }
        ]
      },
      "answers": [],
      "gameOver": -1
    },
    {
      "imageUrl": "",
      "title": {
        "en": "No more steps for You",
        "ru": "Ходов больше не осталось"
      },
      "text": {
        "en": "(ENG) Похоже нам больше нечем вас удивить... ждите продолжения игры!",
        "ru": "Похоже нам больше нечем вас удивить... ждите продолжения игры!"
      },
      "type": 3,
      "voiceUrl": {
        "ru": "",
        "en": ""
      },
      "conditionBlock": {
        "type": 1,
        "conditions": [
          {
            "variableCode": "STEP",
            "sign": 3,
            "value": 50
          }
        ]
      },
      "answers": [],
      "gameOver": 1
    }
  ]
}
